mysqlbisect.py
setup.py
mysqlbisect.egg-info/PKG-INFO
mysqlbisect.egg-info/SOURCES.txt
mysqlbisect.egg-info/dependency_links.txt
mysqlbisect.egg-info/entry_points.txt
mysqlbisect.egg-info/requires.txt
mysqlbisect.egg-info/top_level.txt